README.rst
setup.cfg
setup.py
tornado_razorpay/__init__.py
tornado_razorpay/client.py
tornado_razorpay.egg-info/PKG-INFO
tornado_razorpay.egg-info/SOURCES.txt
tornado_razorpay.egg-info/dependency_links.txt
tornado_razorpay.egg-info/requires.txt
tornado_razorpay.egg-info/top_level.txt