Metadata-Version: 1.1
Name: tornado-razorpay
Version: 0.1.3
Summary: Razorpay Asynchronous Tornado Python Client
Home-page: https://github.com/nkanish2002/tornado-razorpay
Author: Anish Gupta
Author-email: nkanish2002@gmail.com
License: MIT
Keywords: razorpay payment gateway india tornado async
Platform: UNKNOWN
Classifier: Development Status :: 4 - Beta
Classifier: Intended Audience :: Developers
Classifier: License :: OSI Approved :: MIT License
Classifier: Programming Language :: Python
Classifier: Programming Language :: Python :: 3
Classifier: Topic :: Software Development :: Libraries :: Python Modules
